MANIFEST.in
setup.py
analytics/__init__.py
analytics/middleware.py
analytics/models.py
analytics/urls.py
analytics/utils.py
analytics/wsgi.py
appcubator_analytics.egg-info/PKG-INFO
appcubator_analytics.egg-info/SOURCES.txt
appcubator_analytics.egg-info/dependency_links.txt
appcubator_analytics.egg-info/top_level.txt