Metadata-Version: 1.0
Name: appcubator-analytics
Version: 0.1.0
Summary: Appcubator Analytics
Home-page: https://github.com/appcubator/appcubator-analytics
Author: Appcubator
Author-email: team@appcubator.com
License: UNKNOWN
Platform: UNKNOWN
